deepview/datasets/generators/__init__.py
deepview/datasets/generators/core.py
deepview/datasets/generators/detection.py
deepview/datasets/readers/__init__.py
deepview/datasets/readers/arrow.py
deepview/datasets/readers/coco.py
deepview/datasets/readers/core.py
deepview/datasets/readers/csv.py
deepview/datasets/readers/darknet.py
deepview/datasets/readers/pascal.py
deepview/datasets/utils/progress.py
deepview/datasets/writers/__init__.py
deepview/datasets/writers/core.py
deepview/datasets/writers/polars.py
deepview_datasets-0.3.5.dist-info/LICENSE
deepview_datasets-0.3.5.dist-info/METADATA
deepview_datasets-0.3.5.dist-info/WHEEL
deepview_datasets-0.3.5.dist-info/top_level.txt
deepview_datasets-0.3.5.dist-info/RECORD
