Metadata-Version: 2.1
Name: deepview-datasets
Version: 0.3.5
Summary: DeepView Datasets
Author-email: Au-Zone Technologies <info@au-zone.com>
License: DUAL-LICENSED UNDER AGPL-3.0 OR DEEPVIEW AI MIDDLEWARE COMMERCIAL LICENSE
Project-URL: Homepage, https://github.com/DeepViewML/deepview-datasets
Keywords: feed,reader,tutorial
Classifier: Programming Language :: Python
Classifier: Programming Language :: Python :: 3
Requires-Python: >=3.8
License-File: LICENSE
Requires-Dist: pillow
Requires-Dist: polars
Provides-Extra: dev
Requires-Dist: bumpver ; extra == 'dev'
